[
    {
        "text": "VDD",
        "confidence": 0.9924386778920681,
        "bbox": [
            338,
            8,
            386,
            8,
            386,
            32,
            338,
            32
        ]
    },
    {
        "text": "12",
        "confidence": 0.6166470850823662,
        "bbox": [
            334,
            44,
            358,
            44,
            358,
            68,
            334,
            68
        ]
    },
    {
        "text": "Vb1",
        "confidence": 0.7022848667053988,
        "bbox": [
            38,
            124,
            78,
            124,
            78,
            148,
            38,
            148
        ]
    },
    {
        "text": "Mz",
        "confidence": 0.42628107709878593,
        "bbox": [
            156,
            138,
            194,
            138,
            194,
            162,
            156,
            162
        ]
    },
    {
        "text": "M4",
        "confidence": 0.9830637948797406,
        "bbox": [
            241,
            139,
            277,
            139,
            277,
            159,
            241,
            159
        ]
    },
    {
        "text": "Mi",
        "confidence": 0.3833677478218387,
        "bbox": [
            160,
            174,
            192,
            174,
            192,
            198,
            160,
            198
        ]
    },
    {
        "text": "Mz",
        "confidence": 0.4206869009755532,
        "bbox": [
            272,
            174,
            310,
            174,
            310,
            198,
            272,
            198
        ]
    },
    {
        "text": "Iss",
        "confidence": 0.9992739949554992,
        "bbox": [
            254,
            230,
            290,
            230,
            290,
            254,
            254,
            254
        ]
    },
    {
        "text": "Vout",
        "confidence": 0.9993317127227783,
        "bbox": [
            212,
            89,
            260,
            100,
            255,
            120,
            207,
            109
        ]
    },
    {
        "text": "Vin",
        "confidence": 0.5063289403915405,
        "bbox": [
            38,
            188,
            74,
            197,
            69,
            215,
            33,
            207
        ]
    }
]