[
  {
    "component": "MOSFET",
    "pin_index": 2,
    "pin_side": "left",
    "x": 121,
    "y": 140,
    "net_id": 17
  },
  {
    "component": "MOSFET",
    "pin_index": 3,
    "pin_side": "right",
    "x": 293,
    "y": 139,
    "net_id": 18
  },
  {
    "component": "MOSFET",
    "pin_index": 2,
    "pin_side": "left",
    "x": 61,
    "y": 140,
    "net_id": 16
  },
  {
    "component": "MOSFET",
    "pin_index": 3,
    "pin_side": "right",
    "x": 105,
    "y": 140,
    "net_id": 17
  },
  {
    "component": "MOSFET",
    "pin_index": 2,
    "pin_side": "left",
    "x": 308,
    "y": 140,
    "net_id": 18
  },
  {
    "component": "MOSFET",
    "pin_index": 3,
    "pin_side": "right",
    "x": 347,
    "y": 140,
    "net_id": 19
  },
  {
    "component": "AC_Source",
    "pin_index": 0,
    "pin_side": "top",
    "x": 206,
    "y": 245,
    "net_id": 28
  },
  {
    "component": "AC_Source",
    "pin_index": 1,
    "pin_side": "bottom",
    "x": 206,
    "y": 271,
    "net_id": 29
  },
  {
    "component": "AC_Source",
    "pin_index": 0,
    "pin_side": "top",
    "x": 207,
    "y": 30,
    "net_id": 1
  },
  {
    "component": "AC_Source",
    "pin_index": 1,
    "pin_side": "bottom",
    "x": 207,
    "y": 63,
    "net_id": 5
  }
]