[
    {
        "text": "VDD",
        "confidence": 0.9976675927214963,
        "bbox": [
            145,
            17,
            209,
            17,
            209,
            55,
            145,
            55
        ]
    },
    {
        "text": "IREF",
        "confidence": 0.9631687998771667,
        "bbox": [
            19,
            87,
            85,
            87,
            85,
            125,
            19,
            125
        ]
    },
    {
        "text": "2WrEF",
        "confidence": 0.5154027869305038,
        "bbox": [
            289,
            187,
            400,
            187,
            400,
            236,
            289,
            236
        ]
    },
    {
        "text": "2/REF",
        "confidence": 0.8773967528346333,
        "bbox": [
            298,
            116,
            384,
            133,
            376,
            168,
            290,
            151
        ]
    },
    {
        "text": "MREF",
        "confidence": 0.9287002682685852,
        "bbox": [
            130,
            122,
            214,
            138,
            206,
            172,
            123,
            156
        ]
    },
    {
        "text": "WrEF",
        "confidence": 0.5061131119728088,
        "bbox": [
            30,
            191,
            112,
            209,
            103,
            243,
            22,
            226
        ]
    },
    {
        "text": "M2 -",
        "confidence": 0.3656595343169647,
        "bbox": [
            219,
            225,
            272,
            238,
            262,
            272,
            210,
            259
        ]
    }
]