[
  {
    "component": "Resistor",
    "pin_index": 0,
    "pin_side": "top",
    "x": 106,
    "y": 208,
    "net_id": 14
  },
  {
    "component": "Resistor",
    "pin_index": 1,
    "pin_side": "bottom",
    "x": 106,
    "y": 244,
    "net_id": 28
  },
  {
    "component": "BJT",
    "pin_index": 2,
    "pin_side": "left",
    "x": 54,
    "y": 153,
    "net_id": 9
  },
  {
    "component": "BJT",
    "pin_index": 3,
    "pin_side": "right",
    "x": 326,
    "y": 152,
    "net_id": 10
  },
  {
    "component": "Resistor",
    "pin_index": 0,
    "pin_side": "top",
    "x": 276,
    "y": 209,
    "net_id": 12
  },
  {
    "component": "Resistor",
    "pin_index": 1,
    "pin_side": "bottom",
    "x": 276,
    "y": 244,
    "net_id": 28
  },
  {
    "component": "BJT",
    "pin_index": 3,
    "pin_side": "right",
    "x": 242,
    "y": 65,
    "net_id": 3
  }
]